README.md
setup.py
socialist/__init__.py
socialist/cli.py
socialist/profile.py
socialist/socialist.py
socialist.egg-info/PKG-INFO
socialist.egg-info/SOURCES.txt
socialist.egg-info/dependency_links.txt
socialist.egg-info/entry_points.txt
socialist.egg-info/requires.txt
socialist.egg-info/top_level.txt