Metadata-Version: 1.1
Name: socialist
Version: 0.1.0
Summary: UNKNOWN
Home-page: https://github.com/OverwatchHeir/SociaList
Author: OverwatchHeir
Author-email: softw.dev@protonmail.com
License: GNU
Download-URL: https://github.com/OverwatchHeir/SociaList/archive/master.zip
Platform: UNKNOWN
Classifier: Topic :: Utilities
Classifier: Natural Language :: English
Classifier: Programming Language :: Python :: 3.7
